README.rst
setup.py
biscuit/__init__.py
biscuit/__main__.py
biscuit/_version.py
biscuit_py.egg-info/PKG-INFO
biscuit_py.egg-info/SOURCES.txt
biscuit_py.egg-info/dependency_links.txt
biscuit_py.egg-info/entry_points.txt
biscuit_py.egg-info/not-zip-safe
biscuit_py.egg-info/requires.txt
biscuit_py.egg-info/top_level.txt