Metadata-Version: 1.1
Name: biscuit-py
Version: 0.1.2
Summary: biscuit-py decrypts secrets managed by Biscuit.
Home-page: https://github.com/dcoker/biscuit-py/
Author: Doug Coker
Author-email: dcoker@gmail.com
License: https://www.apache.org/licenses/LICENSE-2.0
Platform: UNKNOWN
Classifier: Development Status :: 4 - Beta
Classifier: Intended Audience :: Developers
Classifier: License :: OSI Approved :: Apache Software License
Classifier: Programming Language :: Python :: 2.7
